epsilonq-0.1.0.dist-info/licenses/LICENSE
my_rl_package/__init__.py
my_rl_package/core.py
epsilonq-0.1.0.dist-info/METADATA
epsilonq-0.1.0.dist-info/WHEEL
epsilonq-0.1.0.dist-info/top_level.txt
epsilonq-0.1.0.dist-info/RECORD
