Metadata-Version: 2.4
Name: epsilonq
Version: 0.1.0
Summary: Lightweight RL utilities: epsilon-greedy and Q-learning update
Home-page: https://pypi.org/project/epsilonq/
Author: Krish Makhija
Author-email: krish.makhija2@gmail.com
Classifier: Programming Language :: Python :: 3
Classifier: License :: OSI Approved :: MIT License
Classifier: Operating System :: OS Independent
Requires-Python: >=3.6
License-File: LICENSE
Dynamic: author
Dynamic: author-email
Dynamic: classifier
Dynamic: description
Dynamic: description-content-type
Dynamic: home-page
Dynamic: license-file
Dynamic: requires-python
Dynamic: summary
